libz.so.1
pyBAScloudAPI.cpython-37m-aarch64-linux-gnu.so
libfmt.so.7.1.3
libcurl.so
libcpr.so.1
libz.so
libfmt.so
libcpr.so.1.6
libfmt.so.7
libcpr.so
libBAScloudAPI.so
libz.so.1.2.11.zlib-ng
pyBAScloudAPI-0.3.1.dist-info/LICENSE
pyBAScloudAPI-0.3.1.dist-info/METADATA
pyBAScloudAPI-0.3.1.dist-info/top_level.txt
pyBAScloudAPI-0.3.1.dist-info/RECORD
pyBAScloudAPI-0.3.1.dist-info/WHEEL
pyBAScloudAPI.libs/libcom_err-057ba42b.so.2.1
pyBAScloudAPI.libs/libfmt-8418d76a.so.7
pyBAScloudAPI.libs/libz-b5048ed5.so.1
pyBAScloudAPI.libs/libselinux-ae24b712.so.1
pyBAScloudAPI.libs/libkrb5-d3f87200.so.3.3
pyBAScloudAPI.libs/libkeyutils-19c64d08.so.1.5
pyBAScloudAPI.libs/libcpr-33b9a9da.so.1
pyBAScloudAPI.libs/libgssapi_krb5-fec99a71.so.2.2
pyBAScloudAPI.libs/libBAScloudAPI-b907c232.so
pyBAScloudAPI.libs/libpcre-6b975b27.so.1.2.0
pyBAScloudAPI.libs/libk5crypto-47ac5e52.so.3.1
pyBAScloudAPI.libs/libcrypto-781dd786.so.1.0.2k
pyBAScloudAPI.libs/libkrb5support-400ddc8a.so.0.1
pyBAScloudAPI.libs/libssl-54499ca7.so.1.0.2k
