Metadata-Version: 2.1
Name: pyBAScloudAPI
Version: 0.3.1
Summary: A Python package providing binding for the BAScloud API endpoints.
Home-page: UNKNOWN
Author: ProFM Facility & Project Management GmbH
Author-email: info@profm-gmbh.de
License: UNKNOWN
Platform: UNKNOWN
License-File: LICENSE
